CHANGELOG.rst
COPYING
COPYING.LESSER
MANIFEST.in
README.rst
setup.py
fmn/__init__.py
fmn.consumer.egg-info/PKG-INFO
fmn.consumer.egg-info/SOURCES.txt
fmn.consumer.egg-info/dependency_links.txt
fmn.consumer.egg-info/entry_points.txt
fmn.consumer.egg-info/namespace_packages.txt
fmn.consumer.egg-info/not-zip-safe
fmn.consumer.egg-info/requires.txt
fmn.consumer.egg-info/top_level.txt
fmn/consumer/__init__.py
fmn/consumer/backend.py
fmn/consumer/consumer.py
fmn/consumer/fmn_fasshim.py
fmn/consumer/producer.py
fmn/consumer/util.py
fmn/consumer/worker.py
fmn/consumer/backends/__init__.py
fmn/consumer/backends/android.py
fmn/consumer/backends/base.py
fmn/consumer/backends/debug.py
fmn/consumer/backends/irc.py
fmn/consumer/backends/mail.py
systemd/fmn-backend@.service
systemd/fmn-worker@.service