Metadata-Version: 1.1
Name: fmn.consumer
Version: 1.0.2
Summary: Backend worker daemon for Fedora Notifications
Home-page: https://github.com/fedora-infra/fmn.consumer/
Author: Ralph Bean
Author-email: rbean@redhat.com
License: LGPLv2+
Download-URL: https://pypi.python.org/pypi/fmn.consumer/
Platform: UNKNOWN
Classifier: Environment :: Web Environment
Classifier: Topic :: Software Development :: Libraries :: Python Modules
Classifier: Intended Audience :: Developers
Classifier: Programming Language :: Python
